{"gtabs":[{"panes":[{"ptabs":[{"history":[{"dir":"/home/arch/Music","file":"Kawaii","relpos":6,"ts":1621975436},{"dir":"/home/arch","file":"..","relpos":0,"ts":1621975436},{"dir":"/home","file":"arch","relpos":1,"ts":1621975436},{"dir":"/home/arch","file":"Documents","relpos":14,"ts":1621975436},{"dir":"/home/arch/Music/Kawaii","file":"Future Bass (Kawaii)","relpos":1,"ts":1621975436},{"dir":"/home/arch/Music","file":"Kawaii","relpos":6,"ts":1621975436},{"dir":"/home/arch","file":"..","relpos":0,"ts":1621975436},{"dir":"/home","file":"arch","relpos":1,"ts":1621975436},{"dir":"/home/arch","file":"Documents","relpos":14,"ts":1621975436},{"dir":"/home/arch/Documents","file":"..","relpos":0,"ts":1622014254},{"dir":"/home/arch","file":"Pictures","relpos":19,"ts":1622286543},{"dir":"/home/arch/Documents/Photoshop Plugins","file":"..","relpos":0,"ts":1622308618},{"dir":"/home/arch/Documents","file":"Photoshop Plugins","relpos":7,"ts":1622308618},{"dir":"/home/arch","file":"..","relpos":0,"ts":1622308618},{"dir":"/home","file":"..","relpos":0,"ts":1622308618},{"dir":"/","file":"web","relpos":21,"ts":1622308618},{"dir":"/web","file":"tstudio.lv","relpos":2,"ts":1622308618},{"dir":"/web/tstudio.lv","file":"html","relpos":1,"ts":1622308618},{"dir":"/web/tstudio.lv/html","file":"wp-includes","relpos":4,"ts":1622308618},{"dir":"/web/tstudio.lv/html/wp-includes","file":"..","relpos":0,"ts":1622308618},{"dir":"/web/tstudio.lv/html","file":"cgi-bin","relpos":1,"ts":1622308618},{"dir":"/web/tstudio.lv/html/cgi-bin","file":"..","relpos":0,"ts":1622308618},{"dir":"/web/tstudio.lv/html","file":"wp-admin","relpos":2,"ts":1622308618},{"dir":"/web/tstudio.lv","file":"html","relpos":1,"ts":1622308618},{"dir":"/web/tstudio.lv/html","file":"wp-admin","relpos":2,"ts":1622308618},{"dir":"/web/tstudio.lv/html/wp-admin","file":"images","relpos":2,"ts":1622308618},{"dir":"/web/tstudio.lv/html/wp-admin/images","file":"..","relpos":0,"ts":1622308618},{"dir":"/web/tstudio.lv/html/wp-admin","file":"images","relpos":2,"ts":1622308618},{"dir":"/web/tstudio.lv/html","file":"wp-content","relpos":3,"ts":1622308618},{"dir":"/web/tstudio.lv/html/wp-content","file":"..","relpos":0,"ts":1622308618},{"dir":"/web/tstudio.lv/html","file":"wp-includes","relpos":4,"ts":1622308618},{"dir":"/web/tstudio.lv/html/wp-includes","file":"..","relpos":0,"ts":1622308618},{"dir":"/web/tstudio.lv/html","file":"..","relpos":0,"ts":1622308618},{"dir":"/web/tstudio.lv","file":"..","relpos":0,"ts":1622308618},{"dir":"/web","file":"..","relpos":0,"ts":1622308618},{"dir":"/","file":"web","relpos":21,"ts":1622308618},{"dir":"/web","file":"tstudio.lv","relpos":2,"ts":1622308618},{"dir":"/web/tstudio.lv","file":"html","relpos":1,"ts":1622308618},{"dir":"/web/tstudio.lv/html","file":"wp-content","relpos":3,"ts":1622308618},{"dir":"/web/tstudio.lv/html/wp-content","file":"maintenance","relpos":4,"ts":1622308618},{"dir":"/web/tstudio.lv/html/wp-content/maintenance","file":"..","relpos":0,"ts":1622308618},{"dir":"/web/tstudio.lv/html/wp-content","file":"maintenance","relpos":4,"ts":1622308618},{"dir":"/web/tstudio.lv/html","file":"wp-content","relpos":3,"ts":1622308618},{"dir":"/web/tstudio.lv/html/wp-content","file":"maintenance","relpos":4,"ts":1622308618},{"dir":"/web/tstudio.lv/html/wp-content/maintenance","file":"..","relpos":0,"ts":1622308618},{"dir":"/web/tstudio.lv/html/wp-content","file":"maintenance","relpos":4,"ts":1622308618},{"dir":"/web/tstudio.lv/html","file":"..","relpos":0,"ts":1622308618},{"dir":"/web/tstudio.lv","file":"html","relpos":1,"ts":1622622004},{"dir":"/web","file":"tstudio.lv","relpos":3,"ts":1622622004},{"dir":"/web/tstudio.lv","file":"..","relpos":0,"ts":1622622004},{"dir":"/web","file":"..","relpos":0,"ts":1622622004},{"dir":"/","file":"web","relpos":21,"ts":1622622004},{"dir":"/web","file":"..","relpos":0,"ts":1622622004},{"dir":"/","file":"web","relpos":21,"ts":1622622004},{"dir":"/web","file":"tstudio.lv","relpos":3,"ts":1622622004},{"dir":"/web/tstudio.lv","file":"html","relpos":1,"ts":1622622004},{"dir":"/web/tstudio.lv/html","file":"..","relpos":0,"ts":1622622004},{"dir":"/web/tstudio.lv","file":"..","relpos":0,"ts":1622728804},{"dir":"/web","file":"tstudio.lv","relpos":3,"ts":1622728804},{"dir":"/web/tstudio.lv","file":"html","relpos":1,"ts":1622730617},{"dir":"/web/tstudio.lv/html","file":"cgi-bin","relpos":1,"ts":1622730617},{"dir":"/web/tstudio.lv/html/cgi-bin","file":"..","relpos":0,"ts":1622813786},{"dir":"/web/tstudio.lv/html","file":"cgi-bin","relpos":1,"ts":1622813786},{"dir":"/web/tstudio.lv","file":"..","relpos":0,"ts":1623140406},{"dir":"/web","file":"example.com","relpos":1,"ts":1623140406},{"dir":"/web/example.com","file":"html","relpos":1,"ts":1623140406},{"dir":"/web/example.com/html","file":"wp-content","relpos":2,"ts":1623140406},{"dir":"/web/example.com/html/wp-content","file":"..","relpos":0,"ts":1623140406},{"dir":"/web/example.com/html","file":"..","relpos":0,"ts":1623140406},{"dir":"/web/example.com","file":"html","relpos":1,"ts":1624031294},{"dir":"/web","file":"example.com","relpos":1,"ts":1624031294},{"dir":"/web/example.com","file":"..","relpos":0,"ts":1624031633},{"dir":"/web","file":"..","relpos":0,"ts":1624031633},{"dir":"/","file":"home","relpos":4,"ts":1624031633},{"dir":"/home","file":"arch","relpos":1,"ts":1624031633},{"dir":"/home/arch","file":"Documents","relpos":29,"ts":1624031633},{"dir":"/home/arch/Documents","file":".git","relpos":1,"ts":1624031633},{"dir":"/home/arch","file":"Pictures","relpos":33,"ts":1624031633},{"dir":"/home/arch/Pictures","file":"Anime Backgrounds","relpos":2,"ts":1624031633},{"dir":"/home/arch/Pictures/Anime Backgrounds","file":"..","relpos":0,"ts":1624031633},{"dir":"/home/arch/Pictures","file":"..","relpos":0,"ts":1624032525},{"dir":"/home/arch","file":"www","relpos":12,"ts":1624033977},{"dir":"/home/arch/www","file":"tstudio.lv","relpos":1,"ts":1624033977},{"dir":"/home/arch/www/tstudio.lv","file":"html","relpos":1,"ts":1624033977},{"dir":"/home/arch/www/tstudio.lv/html","file":"..","relpos":0,"ts":1624033977},{"dir":"/home/arch/www/tstudio.lv","file":"..","relpos":0,"ts":1624033977},{"dir":"/home/arch/www","file":"tstudio.lv","relpos":1,"ts":1624033977},{"dir":"/home/arch/www/tstudio.lv","file":"html","relpos":1,"ts":1624033977},{"dir":"/home/arch/www/tstudio.lv/html","file":"..","relpos":0,"ts":1624033977},{"dir":"/home/arch/www/tstudio.lv","file":"..","relpos":0,"ts":1624033977},{"dir":"/home/arch/www","file":"..","relpos":0,"ts":1624033977},{"dir":"/home/arch","file":"Pictures","relpos":12,"ts":1624033977},{"dir":"/home/arch/Pictures","file":"Arch Linux","relpos":5,"ts":1624038367},{"dir":"/home/arch/Pictures/Arch Linux","file":"..","relpos":0,"ts":1624038367},{"dir":"/home/arch/Pictures","file":"Facebook Emojis","relpos":9,"ts":1624038367},{"dir":"/home/arch/Pictures/Facebook Emojis","file":"..","relpos":0,"ts":1624038367},{"dir":"/home/arch/Pictures","file":"Nude","relpos":12,"ts":1624038367},{"dir":"/home/arch/Pictures/Nude","file":"..","relpos":0,"ts":1624038367},{"dir":"/home/arch/Pictures","file":"Wallpapers","relpos":12,"ts":1624038367},{"dir":"/home/arch/Pictures/Wallpapers","file":"wp5849941-retro-80s-wallpapers.jpg","relpos":48,"ts":1624038367}],"filters":{"invert":true,"dot":false,"manual":"","auto":""},"last-location":"/home/arch/Pictures/Wallpapers","sorting":[2],"preview":false}]},{"ptabs":[{"history":[{"dir":"/home/arch","file":"Pictures","relpos":7,"ts":1621974958},{"dir":"/home/arch/Pictures","file":"Screenshot from 2021-05-20 16-36-08.png","relpos":24,"ts":1621974958},{"dir":"/home/arch","file":"Music","relpos":6,"ts":1621974958},{"dir":"/home","file":"arch","relpos":1,"ts":1621974958},{"dir":"/home/arch","file":"Pictures","relpos":7,"ts":1621974958},{"dir":"/home/arch/Pictures","file":"GoPro","relpos":9,"ts":1621974958},{"dir":"/home/arch/Pictures/GoPro","file":"..","relpos":0,"ts":1621974958},{"dir":"/home/arch/Pictures","file":"..","relpos":0,"ts":1621974958},{"dir":"/home/arch","file":"Documents","relpos":3,"ts":1621974958},{"dir":"/home/arch/Documents","file":"Arch Linux","relpos":2,"ts":1621974958},{"dir":"/home/arch","file":"Love","relpos":5,"ts":1621974958},{"dir":"/home/arch/Love","file":"..","relpos":0,"ts":1621974958},{"dir":"/home/arch","file":"Love","relpos":5,"ts":1621974958},{"dir":"/home","file":"arch","relpos":1,"ts":1621974958},{"dir":"/","file":"root","relpos":12,"ts":1621974958},{"dir":"/root","file":"..","relpos":0,"ts":1621974958},{"dir":"/","file":"home","relpos":4,"ts":1621974958},{"dir":"/home","file":"arch","relpos":1,"ts":1621974958},{"dir":"/home/arch","file":"Downloads","relpos":4,"ts":1621974958},{"dir":"/home/arch/Downloads","file":"..","relpos":0,"ts":1621974958},{"dir":"/home/arch","file":"Downloads","relpos":4,"ts":1621974958},{"dir":"/home","file":"arch","relpos":1,"ts":1621975287},{"dir":"/home/arch","file":"Downloads","relpos":4,"ts":1621975287},{"dir":"/home/arch/Downloads","file":"..","relpos":0,"ts":1621975287},{"dir":"/home/arch","file":"Pictures","relpos":7,"ts":1621975287},{"dir":"/home/arch/Pictures","file":"Wallpapers","relpos":18,"ts":1621975287},{"dir":"/home/arch/Pictures/Wallpapers","file":"..","relpos":0,"ts":1621975287},{"dir":"/home/arch/Pictures","file":"Nude","relpos":13,"ts":1621975287},{"dir":"/home","file":"arch","relpos":1,"ts":1621975287},{"dir":"/home/arch","file":"Downloads","relpos":4,"ts":1621975287},{"dir":"/home/arch/Downloads","file":"..","relpos":0,"ts":1621975287},{"dir":"/home/arch","file":"Pictures","relpos":7,"ts":1621975287},{"dir":"/home/arch/Pictures","file":"Wallpapers","relpos":18,"ts":1621975287},{"dir":"/home/arch/Pictures/Wallpapers","file":"..","relpos":0,"ts":1621975287},{"dir":"/home/arch/Pictures","file":"..","relpos":0,"ts":1621975287},{"dir":"/home/arch","file":"Desktop","relpos":2,"ts":1622622004},{"dir":"/home/arch/Desktop","file":"..","relpos":0,"ts":1622622004},{"dir":"/home/arch","file":"Music","relpos":6,"ts":1622622004},{"dir":"/home/arch/Music","file":"..","relpos":0,"ts":1622622004},{"dir":"/home/arch","file":"..","relpos":0,"ts":1622622004},{"dir":"/home","file":"arch","relpos":1,"ts":1622622004},{"dir":"/home/arch","file":"Pictures","relpos":7,"ts":1622622004},{"dir":"/home/arch/Pictures","file":"..","relpos":0,"ts":1622622004},{"dir":"/home/arch","file":"Documents","relpos":3,"ts":1622622004},{"dir":"/home/arch/Documents","file":"..","relpos":0,"ts":1622622004},{"dir":"/home/arch","file":"Videos","relpos":10,"ts":1622622004},{"dir":"/home/arch/Videos","file":"..","relpos":0,"ts":1622622004},{"dir":"/home/arch","file":"amdgpu-pro","relpos":12,"ts":1622622004},{"dir":"/home/arch/amdgpu-pro","file":"..","relpos":0,"ts":1622622004},{"dir":"/home/arch","file":"amdgpu-pro-libgl","relpos":13,"ts":1622622004},{"dir":"/home/arch/amdgpu-pro-libgl","file":"etc","relpos":1,"ts":1622622004},{"dir":"/home/arch/amdgpu-pro-libgl/etc","file":"..","relpos":0,"ts":1622622004},{"dir":"/home/arch/amdgpu-pro-libgl","file":"etc","relpos":1,"ts":1622622004},{"dir":"/home/arch","file":"amdgpu-pro","relpos":12,"ts":1622622004},{"dir":"/home/arch/amdgpu-pro","file":"..","relpos":0,"ts":1622622004},{"dir":"/home/arch","file":"amdgpu-pro","relpos":12,"ts":1622622004},{"dir":"/home/arch/amdgpu-pro","file":"..","relpos":0,"ts":1622622004},{"dir":"/home/arch","file":"Music","relpos":6,"ts":1622622004},{"dir":"/home/arch/Music","file":"..","relpos":0,"ts":1622622004},{"dir":"/home/arch","file":"Music","relpos":6,"ts":1622622004},{"dir":"/home","file":"arch","relpos":1,"ts":1622728804},{"dir":"/home/arch","file":"Documents","relpos":3,"ts":1622728804},{"dir":"/home/arch/Documents","file":"..","relpos":0,"ts":1622813786},{"dir":"/home/arch","file":"Templates","relpos":9,"ts":1622813786},{"dir":"/home/arch/Templates","file":"..","relpos":0,"ts":1622813786},{"dir":"/home/arch","file":"Downloads","relpos":4,"ts":1622813786},{"dir":"/home/arch/Downloads","file":"..","relpos":0,"ts":1622813786},{"dir":"/home/arch","file":"Documents","relpos":3,"ts":1622813786},{"dir":"/home/arch/Documents","file":"..","relpos":0,"ts":1622813786},{"dir":"/home/arch","file":"Pictures","relpos":7,"ts":1622813786},{"dir":"/home/arch/Pictures","file":"..","relpos":0,"ts":1622813786},{"dir":"/home/arch","file":"Videos","relpos":10,"ts":1622813786},{"dir":"/home/arch/Videos","file":"..","relpos":0,"ts":1622813786},{"dir":"/home/arch","file":"amdgpu-pro","relpos":12,"ts":1622813786},{"dir":"/home/arch/amdgpu-pro","file":"..","relpos":0,"ts":1622813786},{"dir":"/home/arch","file":"Documents","relpos":3,"ts":1622813786},{"dir":"/home/arch/Documents","file":"Deemix","relpos":5,"ts":1623271877},{"dir":"/home/arch/Documents/Deemix","file":"..","relpos":0,"ts":1623365328},{"dir":"/home/arch/Documents","file":"Facebook Leak [2019][533M Records][106 Countries]","relpos":6,"ts":1623365328},{"dir":"/home/arch/Documents/Facebook Leak [2019][533M Records][106 Countries]","file":"..","relpos":0,"ts":1623365328},{"dir":"/home/arch/Documents","file":"..","relpos":0,"ts":1623365328},{"dir":"/home/arch","file":"Pictures","relpos":7,"ts":1623688370},{"dir":"/home/arch/Pictures","file":"Anime Backgrounds","relpos":1,"ts":1623688370},{"dir":"/home/arch/Pictures/Anime Backgrounds","file":"..","relpos":0,"ts":1623688370},{"dir":"/home/arch/Pictures","file":"NIKON","relpos":12,"ts":1624038367},{"dir":"/home/arch/Pictures/NIKON","file":"BILDES","relpos":1,"ts":1624038367},{"dir":"/home/arch/Pictures/NIKON/BILDES","file":"HOLI and Casual","relpos":1,"ts":1624038367},{"dir":"/home/arch/Pictures/NIKON/BILDES/HOLI and Casual","file":"..","relpos":0,"ts":1624038367},{"dir":"/home/arch/Pictures/NIKON/BILDES","file":"..","relpos":0,"ts":1624038367},{"dir":"/home/arch/Pictures/NIKON","file":"..","relpos":0,"ts":1624038367},{"dir":"/home/arch/Pictures","file":"..","relpos":0,"ts":1624038367},{"dir":"/home/arch","file":"Videos","relpos":10,"ts":1624038367},{"dir":"/home/arch/Videos","file":"OBS Records","relpos":1,"ts":1624038367},{"dir":"/home/arch/Videos/OBS Records","file":"..","relpos":0,"ts":1624038367},{"dir":"/home/arch/Videos","file":"..","relpos":0,"ts":1624038367},{"dir":"/home/arch","file":"..","relpos":0,"ts":1624038367},{"dir":"/home","file":"arch","relpos":1,"ts":1624038367},{"dir":"/home/arch","file":"Documents","relpos":3,"ts":1624038367},{"dir":"/home","file":"..","relpos":0,"ts":1624197182},{"dir":"/","file":"home","relpos":4,"ts":1624197182}],"filters":{"invert":true,"dot":true,"manual":"","auto":""},"last-location":"/","sorting":[2],"preview":false}]}],"active-pane":0,"preview":false,"splitter":{"pos":-1,"ratio":0.5,"orientation":"v","expanded":false}}],"trash":[{"trashed":"/home/arch/.local/share/vifm/Trash/000_._.DS_Store","original":"/home/arch/._.DS_Store"}],"marks":{"H":{"dir":"/home/arch/","file":"..","ts":1621974065},"b":{"dir":"/home/arch/bin/","file":"..","ts":1621974065},"h":{"dir":"/home/arch/","file":"..","ts":1621974065},"z":{"dir":"/home/arch/.config/vifm","file":"..","ts":1621974065}},"bmarks":{},"cmd-hist":[{"text":"colorscheme palenight","ts":1621974504},{"text":"i","ts":1621975287},{"text":"zo","ts":1621975436},{"text":"q","ts":1622464692}],"search-hist":[{"text":"blog","ts":1622308618}],"regs":{"\"":["/home/arch/.local/share/vifm/Trash/000_._.DS_Store"]},"dir-stack":[],"use-term-multiplexer":false}